langml/__init__.py
langml/activations.py
langml/cli.py
langml/log.py
langml/model.py
langml/tensor_typing.py
langml/tokenizer.py
langml/utils.py
langml/baselines/__init__.py
langml/baselines/cli.py
langml/baselines/clf/__init__.py
langml/baselines/clf/bert.py
langml/baselines/clf/bilstm.py
langml/baselines/clf/cli.py
langml/baselines/clf/dataloader.py
langml/baselines/clf/textcnn.py
langml/baselines/contrastive/__init__.py
langml/baselines/contrastive/cli.py
langml/baselines/contrastive/utils.py
langml/baselines/contrastive/simcse/__init__.py
langml/baselines/contrastive/simcse/dataloder.py
langml/baselines/contrastive/simcse/model.py
langml/baselines/matching/__init__.py
langml/baselines/matching/cli.py
langml/baselines/matching/sbert/__init__.py
langml/baselines/matching/sbert/dataloder.py
langml/baselines/matching/sbert/model.py
langml/baselines/ner/__init__.py
langml/baselines/ner/bert_crf.py
langml/baselines/ner/cli.py
langml/baselines/ner/dataloader.py
langml/baselines/ner/lstm_crf.py
langml/common/__init__.py
langml/common/evaluator/__init__.py
langml/common/evaluator/spearman.py
langml/layers/__init__.py
langml/layers/attention.py
langml/layers/crf.py
langml/layers/layer_norm.py
langml/layers/layers.py
langml/plm/__init__.py
langml/plm/albert.py
langml/plm/bert.py
langml/plm/layers.py
langml/prompt/__init__.py
langml/prompt/base.py
langml/prompt/clf/__init__.py
langml/prompt/clf/ptuning.py
langml/prompt/clf/utils.py
langml/prompt/models/__init__.py
langml/prompt/models/ptuning.py
langml/third_party/__init__.py
langml/third_party/conlleval.py
langml/third_party/crf.py
langml/transformer/__init__.py
langml/transformer/encoder.py
langml/transformer/layers.py
langml-0.4.2.dist-info/LICENSE
langml-0.4.2.dist-info/METADATA
langml-0.4.2.dist-info/WHEEL
langml-0.4.2.dist-info/entry_points.txt
langml-0.4.2.dist-info/top_level.txt
langml-0.4.2.dist-info/RECORD
