Metadata-Version: 2.1
Name: langml
Version: 0.4.2
Summary: A Keras-based and TensorFlow-backend language model toolkit.
Home-page: https://github.com/4AI/langml
Author: seanlee
Author-email: xmlee97@gmail.com
License: UNKNOWN
Platform: all
Classifier: Intended Audience :: Developers
Classifier: Operating System :: OS Independent
Classifier: License :: OSI Approved :: MIT License
Classifier: Programming Language :: Python
Classifier: Programming Language :: Python :: 3
Classifier: Programming Language :: Python :: 3.6
Classifier: Programming Language :: Python :: 3.7
Classifier: Programming Language :: Python :: 3.8
Classifier: Topic :: Text Processing
Classifier: Topic :: Text Processing :: Indexing
Classifier: Topic :: Text Processing :: Linguistic
